microsoft_agents/hosting/core/__init__.py
microsoft_agents/hosting/core/activity_handler.py
microsoft_agents/hosting/core/agent.py
microsoft_agents/hosting/core/card_factory.py
microsoft_agents/hosting/core/channel_adapter.py
microsoft_agents/hosting/core/channel_api_handler_protocol.py
microsoft_agents/hosting/core/channel_service_adapter.py
microsoft_agents/hosting/core/channel_service_client_factory_base.py
microsoft_agents/hosting/core/message_factory.py
microsoft_agents/hosting/core/middleware_set.py
microsoft_agents/hosting/core/rest_channel_service_client_factory.py
microsoft_agents/hosting/core/turn_context.py
microsoft_agents/hosting/core/app/__init__.py
microsoft_agents/hosting/core/app/agent_application.py
microsoft_agents/hosting/core/app/app_error.py
microsoft_agents/hosting/core/app/app_options.py
microsoft_agents/hosting/core/app/input_file.py
microsoft_agents/hosting/core/app/query.py
microsoft_agents/hosting/core/app/route.py
microsoft_agents/hosting/core/app/typing_indicator.py
microsoft_agents/hosting/core/app/oauth/__init__.py
microsoft_agents/hosting/core/app/oauth/auth_handler.py
microsoft_agents/hosting/core/app/oauth/authorization.py
microsoft_agents/hosting/core/app/state/__init__.py
microsoft_agents/hosting/core/app/state/conversation_state.py
microsoft_agents/hosting/core/app/state/state.py
microsoft_agents/hosting/core/app/state/temp_state.py
microsoft_agents/hosting/core/app/state/turn_state.py
microsoft_agents/hosting/core/authorization/__init__.py
microsoft_agents/hosting/core/authorization/access_token_provider_base.py
microsoft_agents/hosting/core/authorization/agent_auth_configuration.py
microsoft_agents/hosting/core/authorization/anonymous_token_provider.py
microsoft_agents/hosting/core/authorization/auth_types.py
microsoft_agents/hosting/core/authorization/authentication_constants.py
microsoft_agents/hosting/core/authorization/claims_identity.py
microsoft_agents/hosting/core/authorization/connections.py
microsoft_agents_hosting_core-0.3.2.dist-info/METADATA
microsoft_agents_hosting_core-0.3.2.dist-info/WHEEL
microsoft_agents_hosting_core-0.3.2.dist-info/top_level.txt
microsoft_agents_hosting_core-0.3.2.dist-info/RECORD
